AUTHORS.rst
CONTRIBUTING.rst
HISTORY.rst
LICENSE
MANIFEST.in
README.rst
requirements.txt
setup.cfg
setup.py
testpad/__init__.py
testpad/models.py
testpad.egg-info/PKG-INFO
testpad.egg-info/SOURCES.txt
testpad.egg-info/dependency_links.txt
testpad.egg-info/not-zip-safe
testpad.egg-info/requires.txt
testpad.egg-info/top_level.txt
testpad/static/css/testpad/lib/feedback.min.css
testpad/static/css/testpad/lib/icons.png
testpad/static/js/testpad/lib/feedback.js
testpad/static/js/testpad/lib/html2canvas.js
testpad/templates/testpad/base.html