Metadata-Version: 1.1
Name: testpad
Version: 0.1.7
Summary: Screenshot and Annotate and send to django backend.
Home-page: https://github.com/milin/testpad
Author: Milind Shakya
Author-email: sh.milind@gmail.com
License: BSD
Keywords: testpad
Platform: UNKNOWN
Classifier: Development Status :: 3 - Alpha
Classifier: Framework :: Django
Classifier: Intended Audience :: Developers
Classifier: License :: OSI Approved :: BSD License
Classifier: Natural Language :: English
Classifier: Programming Language :: Python :: 2
Classifier: Programming Language :: Python :: 2.7
Classifier: Programming Language :: Python :: 3
Classifier: Programming Language :: Python :: 3.3
Classifier: Programming Language :: Python :: 3.4
